README.rst
setup.cfg
setup.py
./__init__.py
./production.py
./production.xml
./tryton.cfg
./reports/base.html
./reports/bom-tree.html
./reports/production.html
./reports/production_schedule.html
./reports/production_schedule.ods
./reports/css/bootstrap/css/bootstrap.min.css
./reports/css/bootstrap/fonts/glyphicons-halflings-regular.eot
./reports/css/bootstrap/fonts/glyphicons-halflings-regular.svg
./reports/css/bootstrap/fonts/glyphicons-halflings-regular.ttf
./reports/css/bootstrap/fonts/glyphicons-halflings-regular.woff
./reports/css/bootstrap/fonts/glyphicons-halflings-regular.woff2
./reports/css/font-awesome/css/font-awesome.min.css
./reports/css/font-awesome/fonts/FontAwesome.otf
./reports/css/font-awesome/fonts/fontawesome-webfont.eot
./reports/css/font-awesome/fonts/fontawesome-webfont.svg
./reports/css/font-awesome/fonts/fontawesome-webfont.ttf
./reports/css/font-awesome/fonts/fontawesome-webfont.woff
./reports/css/font-awesome/fonts/fontawesome-webfont.woff2
./reports/js/jquery-1.3.2.min.js
./reports/js/jquery-barcode.min.js
./tests/__init__.py
./tests/test_production.py
./tests/test_views_depends.py
./view/report_production_schedule_form.xml
fio_production_report.egg-info/PKG-INFO
fio_production_report.egg-info/SOURCES.txt
fio_production_report.egg-info/dependency_links.txt
fio_production_report.egg-info/entry_points.txt
fio_production_report.egg-info/not-zip-safe
fio_production_report.egg-info/requires.txt
fio_production_report.egg-info/top_level.txt