Metadata-Version: 1.1
Name: fio-production-report
Version: 4.0.0.5
Summary: Collection of Production Reports
Home-page: http://www.fulfil.io/
Author: Fulfil.IO Inc.
Author-email: support@fulfil.io
License: BSD
Platform: UNKNOWN
Classifier: Development Status :: 4 - Beta
Classifier: Environment :: Plugins
Classifier: Intended Audience :: Developers
Classifier: License :: OSI Approved :: BSD License
Classifier: Natural Language :: English
Classifier: Operating System :: OS Independent
Classifier: Programming Language :: Python
Classifier: Framework :: Tryton
Classifier: Topic :: Office/Business
